ess/__init__.py
ess/ess.py
idm/__init__.py
idm/idm.py
IDM_FRESH-1.2.dist-info/METADATA
IDM_FRESH-1.2.dist-info/WHEEL
IDM_FRESH-1.2.dist-info/entry_points.txt
IDM_FRESH-1.2.dist-info/top_level.txt
IDM_FRESH-1.2.dist-info/RECORD
