Metadata-Version: 2.1
Name: IDM-FRESH
Version: 1.2
Summary: SCRIPT UNTUK MENGHASILKAN RIBUAN BARCODE
Home-page: https://github.com/username/my_project
Author: robbii13
Author-email: email@example.com
Requires-Dist: prettytable
Requires-Dist: python-barcode
Requires-Dist: pillow
Requires-Dist: colorama
